setup.py
Alexandersr/__init__.py
Alexandersr/cal.py
Alexandersr/pi.py
Alexandersr.egg-info/PKG-INFO
Alexandersr.egg-info/SOURCES.txt
Alexandersr.egg-info/dependency_links.txt
Alexandersr.egg-info/top_level.txt