Metadata-Version: 2.1
Name: Alexandersr
Version: 0.0.1
Summary: Tarea de modulos de programacion II
Author: Alexander Sanchez
Author-email: alexadersr599@gmail.com
License: MIT
Keywords: testing,logging,example
